pipecatcloud/__init__.py
pipecatcloud/__main__.py
pipecatcloud/__version__.py
pipecatcloud/agent.py
pipecatcloud/api.py
pipecatcloud/config.py
pipecatcloud/constants.py
pipecatcloud/exception.py
pipecatcloud/py.typed
pipecatcloud/session.py
pipecatcloud/_utils/__init__.py
pipecatcloud/_utils/async_utils.py
pipecatcloud/_utils/auth_utils.py
pipecatcloud/_utils/console_utils.py
pipecatcloud/_utils/deploy_utils.py
pipecatcloud/_utils/regions.py
pipecatcloud/cli/__init__.py
pipecatcloud/cli/api.py
pipecatcloud/cli/config.py
pipecatcloud/cli/entry_point.py
pipecatcloud/cli/commands/__init__.py
pipecatcloud/cli/commands/agent.py
pipecatcloud/cli/commands/auth.py
pipecatcloud/cli/commands/deploy.py
pipecatcloud/cli/commands/docker.py
pipecatcloud/cli/commands/organizations.py
pipecatcloud/cli/commands/regions.py
pipecatcloud/cli/commands/secrets.py
pipecatcloud/smallwebrtc/session_manager.py
pipecatcloud-0.2.18.dist-info/licenses/LICENSE
pipecatcloud-0.2.18.dist-info/METADATA
pipecatcloud-0.2.18.dist-info/WHEEL
pipecatcloud-0.2.18.dist-info/entry_points.txt
pipecatcloud-0.2.18.dist-info/top_level.txt
pipecatcloud-0.2.18.dist-info/RECORD
