Metadata-Version: 2.4
Name: pipecatcloud
Version: 0.2.18
Summary: Cloud hosting for Pipecat AI applications
License: BSD 2-Clause License
Project-URL: Website, https://docs.pipecat.daily.co/
Keywords: pipecat,pipecat-ai,voice,ai,llm
Requires-Python: >=3.10
License-File: LICENSE
Requires-Dist: aiohttp<4.0.0,>=3.11.12
Requires-Dist: fastapi<1.0.0,>=0.115.6
Requires-Dist: loguru~=0.7.3
Requires-Dist: python-dotenv<2.0.0,>=1.0.1
Requires-Dist: uvicorn<1.0.0,>=0.32.0
Requires-Dist: typer<1,>=0.20.0
Requires-Dist: synchronicity<1.0.0,>=0.11
Requires-Dist: toml~=0.10.2
Requires-Dist: questionary~=2.1.0
Provides-Extra: pipecat
Requires-Dist: pipecat-ai>=0.0.79; extra == "pipecat"
Dynamic: license-file
